{
  "_expenses": {
    "payms": {
      "0": {
        "id": 0,
        "name": "undefined"
      },
      "1361694372893": {
        "id": 1361694372893,
        "name": "NETS"
      },
      "1363314106821": {
        "id": 1363314106821,
        "name": "Gifts"
      },
      "1363857352962": {
        "id": 1363857352962,
        "name": "Chequeee"
      },
      "1363857357505": {
        "id": 1363857357505,
        "name": "iNets"
      },
      "1363857409977": {
        "id": 1363857409977,
        "name": "Cash"
      },
      "1363949455170": {
        "id": 1363949455170,
        "name": "iBank"
      },
      "1364054074479": {
        "id": 1364054074479,
        "name": "Cash"
      },
      "1364273369381": {
        "id": 1364273369381,
        "name": "Carelessness"
      },
      "1364521902224": {
        "id": 1364521902224,
        "name": "mBank"
      },
      "1365134400063": {
        "id": 1365134400063,
        "name": "Giftsssss"
      }
    },
    "categories": {
      "0": {
        "id": 0,
        "name": "undefined"
      },
      "1363504544188": {
        "id": 1363504544188,
        "name": "Misc"
      },
      "1363942776603": {
        "id": 1363942776603,
        "name": "Food"
      },
      "1365228904230": {
        "id": 1365228904230,
        "name": "eee"
      },
      "1364969707451": {
        "id": 1364969707451,
        "name": "Entertainmentoo"
      },
      "1364969857857": {
        "id": 1364969857857,
        "name": "Entertainmentooooo"
      },
      "1364873536973": {
        "id": 1364873536973,
        "name": "adsf"
      },
      "1363314106821": {
        "id": 1363314106821,
        "name": "Entertainment"
      },
      "1364969975721": {
        "id": 1364969975721,
        "name": "Entertainmente"
      },
      "1364704133024": {
        "id": 1364704133024,
        "name": "Transport"
      },
      "1364969751316": {
        "id": 1364969751316,
        "name": "Entertainmentooo"
      },
      "1365134438535": {
        "id": 1365134438535,
        "name": "Entertainmentsss"
      },
      "1364969813631": {
        "id": 1364969813631,
        "name": "Entertainmentoooo"
      },
      "1364053692757": {
        "id": 1364053692757,
        "name": "Leisure"
      }
    },
    "recordsByCategory": {
      "1364969751316": [],
      "0": [],
      "1365134438535": [],
      "1363504544188": [],
      "1363942776603": [],
      "1364969857857": [],
      "1364969707451": [],
      "1364873536973": [],
      "1363314106821": [
        {
          "expenseType": "NEED",
          "paymentMethod": {
            "id": 1363314106821,
            "name": "Gifts"
          },
          "amount": 99.0,
          "name": "Acer Laptop",
          "remark": "nil",
          "date": "Mar 22, 2013 7:14:33 PM",
          "id": 1363950898967
        }
      ],
      "1364969813631": [],
      "1364969975721": [],
      "1364704133024": []
    }
  },
  "_incomes": {
    "categories": {
      "0": {
        "id": 0,
        "name": "undefined"
      },
      "1363504544188": {
        "id": 1363504544188,
        "name": "Misc"
      },
      "1364097417024": {
        "id": 1364097417024,
        "name": "Gifts"
      },
      "1362480320970": {
        "id": 1362480320970,
        "name": "Allowance"
      },
      "1362122547530": {
        "id": 1362122547530,
        "name": "Salary"
      },
      "1363950844232": {
        "id": 1363950844232,
        "name": "Loot"
      },
      "1363314106821": {
        "id": 1363314106821,
        "name": "Scholarship"
      },
      "1364222095831": {
        "id": 1364222095831,
        "name": "Found"
      },
      "1364935492692": {
        "id": 1364935492692,
        "name": "Bursary"
      }
    },
    "recordsByCategory": {
      "0": [],
      "1363504544188": [],
      "1364097417024": [],
      "1362480320970": [
        {
          "amount": 200.0,
          "name": "Pocket Money",
          "remark": ":\\",
          "date": "Mar 22, 2013 12:36:07 PM",
          "id": 1364133005448
        }
      ],
      "1364222095831": [],
      "1364935492692": [],
      "1363314106821": []
    }
  },
  "_nwsGen": {
    "NEEDS": 0.5,
    "WANTS": 0.3,
    "SAVINGS": 0.2,
    "BUFFER": 0.05,
    "MAXNEEDS": 0.7,
    "MINNEEDS": 0.1,
    "MAXWANTS": 0.5,
    "MINWANTS": 0.1,
    "MAXSAVINGS": 0.7,
    "MINSAVINGS": 0.2,
    "pastMonthNWS": {
      "date": {
        "year": 2013,
        "month": 2,
        "dayOfMonth": 6,
        "hourOfDay": 14,
        "minute": 35,
        "second": 11
      },
      "targetNeedsRatio": 0.6000000000000001,
      "targetWantsRatio": 0.25,
      "targetSavingsRatio": 0.14999999999999986,
      "currentNeeds": 99.0,
      "currentWants": 0.0,
      "currentSavings": 101.0,
      "income": 200.0,
      "isSet": true
    },
    "thisMonthNWS": {
      "date": {
        "year": 2013,
        "month": 3,
        "dayOfMonth": 6,
        "hourOfDay": 18,
        "minute": 20,
        "second": 43
      },
      "targetNeedsRatio": 0.45000000000000023,
      "targetWantsRatio": 0.10000000000000002,
      "targetSavingsRatio": 0.4499999999999998,
      "currentNeeds": 0.0,
      "currentWants": 0.0,
      "currentSavings": 0.0,
      "income": 0.0,
      "isSet": true
    }
  },
  "_targetManager": {
    "mapTarget": {
      "1363314106821": {
        "cat": {
          "id": 1363314106821,
          "name": "Entertainment"
        },
        "targetAmt": 1000.0
      },
      "1363504544188": {
        "cat": {
          "id": 1363504544188,
          "name": "Misc"
        },
        "targetAmt": 11.0
      },
      "1363942776603": {
        "cat": {
          "id": 1363942776603,
          "name": "Food"
        },
        "targetAmt": 100.0
      },
      "1364053692757": {
        "cat": {
          "id": 1364053692757,
          "name": "Leisure"
        },
        "targetAmt": 500.0
      },
      "1364704133024": {
        "cat": {
          "id": 1364704133024,
          "name": "Transport"
        },
        "targetAmt": 80000.0
      },
      "1364969975721": {
        "cat": {
          "id": 1364969975721,
          "name": "Entertainmente"
        },
        "targetAmt": 12.0
      }
    }
  }
}